{
  "id": "P10",
  "name": "Accounts, Tenancy & Tenant-Scoped Knowledge API",
  "objective": "Introduce users/tenants/projects with signup/login/session auth and API credentials; scope the knowledge API (write/read/search) per tenant; seed the operator's own tenant and migrate the live knowledge.hi2vi.com corpus in as tenant #1",
  "status": "planned",
  "order": 1,
  "created_at": "2026-07-16T14:25:27+09:00",
  "started_at": null,
  "completed_at": null,
  "review": {
    "status": "pending",
    "reviewed_at": null,
    "reviewer": null,
    "note": null
  },
  "paths": {
    "phase_md": "phase.md",
    "intent_md": "intent.md",
    "slices_dir": "slices"
  },
  "archive": {
    "archived": false,
    "archived_at": null,
    "archive_path": null
  }
}
